{"cameraMode":{"drawMode":0,"name":"Shaded","section":"Shading Mode"},"sceneLighting":true,"audioPlay":false,"sceneViewState":{"showFog":true,"showMaterialUpdate":false,"showSkybox":true,"showFlares":true,"showImageEffects":true,"showParticleSystems":true},"in2DMode":false,"pivot":{"x":2.7927494049072267,"y":-2.33497953414917,"z":0.09073996543884278},"rotation":{"x":0.2988226115703583,"y":-0.009922325611114502,"z":0.0023401256185024978,"w":0.9547663927078247},"size":17.3450927734375,"orthographic":false}